[
  {
    "name": "io.micronaut.http.poja.sample1.$MyResource$Definition",
    "methods": [
      {
        "name": "<init>",
        "parameterTypes": []
      }
    ]
  },
  {
    "name": "java.security.SecureRandomParameters"
  },
  {
    "name": "sun.security.provider.NativePRNG$NonBlocking",
    "methods": [
      {
        "name": "<init>",
        "parameterTypes": []
      },
      {
        "name": "<init>",
        "parameterTypes": [
          "java.security.SecureRandomParameters"
        ]
      }
    ]
  },
  {
    "name": "java.io.FileDescriptor",
    "allDeclaredConstructors": true
  }
]
